ben_lammps_utils/__init__.py
ben_lammps_utils/convert_to_csv.py
ben_lammps_utils/convert_to_parquet.py
ben_lammps_utils/read_lammps_out.py
ben_lammps_utils/species_quick_plots.py
ben_lammps_utils-0.9.0.dist-info/WHEEL
ben_lammps_utils-0.9.0.dist-info/entry_points.txt
ben_lammps_utils-0.9.0.dist-info/METADATA
ben_lammps_utils-0.9.0.dist-info/RECORD
