Metadata-Version: 2.3
Name: ben-lammps-utils
Version: 0.9.0
Summary: A set of tools for parsing Lammps and ReaxFF output 
Author: Ben
Author-email: Ben <bennyp2494@gmail.com>
Requires-Dist: fastparquet>=2024.11.0
Requires-Dist: matplotlib>=3.9.4
Requires-Dist: pandas>=2.3.2
Requires-Dist: pyarrow>=21.0.0
Requires-Dist: tqdm>=4.67.1
Requires-Python: >=3.9
